{
	"info": {
		"_postman_id": "fa68cbe1-2682-49fa-8848-306598bd6de1",
		"name": "2.ConsultarID",
		"schema": "https://schema.getpostman.com/json/collection/v2.1.0/collection.json"
	},
	"item": [
		{
			"name": "2.1. GET 10ID",
			"event": [
				{
					"listen": "test",
					"script": {
						"id": "e2b3943c-f8db-40a1-b7ea-d733b0ab631f",
						"exec": [
							""
						],
						"type": "text/javascript"
					}
				}
			],
			"request": {
				"method": "GET",
				"header": [],
				"url": {
					"raw": "{{URL}}/store/order/{{id}}",
					"host": [
						"{{URL}}"
					],
					"path": [
						"store",
						"order",
						"{{id}}"
					]
				}
			},
			"response": []
		},
		{
			"name": "2. GET 1 Unitaria",
			"event": [
				{
					"listen": "test",
					"script": {
						"id": "e2b3943c-f8db-40a1-b7ea-d733b0ab631f",
						"exec": [
							""
						],
						"type": "text/javascript"
					}
				}
			],
			"request": {
				"method": "GET",
				"header": [],
				"url": {
					"raw": "{{URL}}/store/order/5",
					"host": [
						"{{URL}}"
					],
					"path": [
						"store",
						"order",
						"5"
					]
				}
			},
			"response": []
		}
	],
	"event": [
		{
			"listen": "prerequest",
			"script": {
				"id": "020f72b4-0615-4aa5-88ea-98bd826f3037",
				"type": "text/javascript",
				"exec": [
					""
				]
			}
		},
		{
			"listen": "test",
			"script": {
				"id": "7dba5df2-6f97-45b5-b405-983a2d93fa43",
				"type": "text/javascript",
				"exec": [
					""
				]
			}
		}
	],
	"protocolProfileBehavior": {}
}